autojinja/__init__.py
autojinja/__main__.py
autojinja/defaults.py
autojinja/exceptions.py
autojinja/main.py
autojinja/parser.py
autojinja/path.py
autojinja/templates.py
autojinja/utils.py
autojinja-1.14.1.dist-info/LICENSE
autojinja-1.14.1.dist-info/METADATA
autojinja-1.14.1.dist-info/WHEEL
autojinja-1.14.1.dist-info/entry_points.txt
autojinja-1.14.1.dist-info/top_level.txt
autojinja-1.14.1.dist-info/RECORD
