Metadata-Version: 2.1
Name: autojinja
Version: 1.14.1
Summary: Content generation with Jinja templates in between comments
Home-page: https://github.com/ldflo/autojinja
Author: Florian Popek
Author-email: florian.popek@gmail.com
License: BSD
Platform: OS Independent
Classifier: Development Status :: 4 - Beta
Classifier: Environment :: Console
Classifier: Intended Audience :: Developers
Classifier: License :: OSI Approved :: BSD License
Classifier: Operating System :: OS Independent
Classifier: Programming Language :: Python :: 3.6
Classifier: Programming Language :: Python :: 3.7
Classifier: Programming Language :: Python :: 3.8
Classifier: Programming Language :: Python :: 3.9
Classifier: Programming Language :: Python :: 3.10
Classifier: Programming Language :: Python :: 3.11
Classifier: Programming Language :: Python :: 3.12
Classifier: Topic :: Software Development :: Code Generators
License-File: LICENSE
Requires-Dist: jinja2
